mymathlib/__init__.py
mymathlib/awikwok.py
mymathlib/test.py
mymathlib-0.0.2.dist-info/METADATA
mymathlib-0.0.2.dist-info/WHEEL
mymathlib-0.0.2.dist-info/top_level.txt
mymathlib-0.0.2.dist-info/RECORD
