Metadata-Version: 2.1
Name: mymathlib
Version: 0.0.2
Summary: A simple Python library for basic mathematical calculations
Home-page: https://github.com/AIvanCP
Author: AIvanCP
Author-email: <angvacp@gmail.com>
License: MIT
Platform: UNKNOWN
Classifier: Development Status :: 1 - Planning
